Kiwiii_server-0.7.0.dist-info/DESCRIPTION.rst
Kiwiii_server-0.7.0.dist-info/METADATA
Kiwiii_server-0.7.0.dist-info/RECORD
Kiwiii_server-0.7.0.dist-info/WHEEL
Kiwiii_server-0.7.0.dist-info/metadata.json
Kiwiii_server-0.7.0.dist-info/top_level.txt
kiwiii/__init__.py
kiwiii/excelexporter.py
kiwiii/handler.py
kiwiii/handlerutil.py
kiwiii/screenerapi.py
kiwiii/sqliteconnection.py
kiwiii/tablebuilder.py
kiwiii/tablecolumn.py
kiwiii/tablefilter.py
kiwiii/worker.py
kiwiii/parser/BiacoreT200.py
kiwiii/parser/EnVision.py
kiwiii/parser/LightCycler480.py
kiwiii/parser/SpectraMaxM2.py
kiwiii/parser/Synergy4.py
kiwiii/parser/__init__.py
kiwiii/parser/helper.py
kiwiii/parser/screener_parser.py
kiwiii/stats/__init__.py
kiwiii/stats/graphgen.py
kiwiii/stats/graphstats.py
legacy/(dep)ssphelper.py
legacy/(dep)test_ssp.py
legacy/__init__.py
legacy/abstractdataframe.py
legacy/adminhandler.py
legacy/basehandler.py
legacy/cairotest.py
legacy/calc_performance.py
legacy/cheddartest.py
legacy/chemlib_dup_alias.py
legacy/datatable.py
legacy/dbhandler.py
legacy/drawtest.py
legacy/graphhandler.py
legacy/iohandler.py
legacy/launcher.py
legacy/listdataframe.py
legacy/merge_aliases.py
legacy/observertest.py
legacy/pandasdataframe.py
legacy/pandastest.py
legacy/performance_test.py
legacy/py2exe.py
legacy/pyqtgraphsample1.py
legacy/pysidetest.py
legacy/rdkittest.py
legacy/rowfunctions.py
legacy/settings.py
legacy/singletontest.py
legacy/test.py
legacy/test_csvsupplier.py
legacy/test_pandasdataframe.py
legacy/workertest.py
legacy/data/__init__.py
legacy/data/dataframe.py
legacy/data/sqliteconnection.py
legacy/data/webdataframe.py
legacy/ext/__init__.py
legacy/ext/chem/__init__.py
legacy/ext/chem/rdchem.py
legacy/ext/gui/__init__.py
legacy/ext/gui/helperwidget.py
legacy/ext/gui/mainwindow.py
legacy/ext/gui/structureviewtab.py
legacy/ext/gui/tableviewtab.py
legacy/ext/gui/threading.py
legacy/ext/gui/menu/__init__.py
legacy/ext/gui/menu/calculateproperties.py
legacy/ext/gui/menu/copy.py
legacy/ext/gui/menu/exporttoexcel.py
legacy/ext/gui/menu/importcsv.py
legacy/ext/gui/menu/importsdfile.py
legacy/ext/gui/menu/newcompoundlist.py
legacy/ext/gui/menu/opendataframe.py
