Metadata-Version: 2.0
Name: Kiwiii-server
Version: 0.7.0
Summary: HTTP API server library for chemical database administration and computation
Home-page: https://github.com/mojaie/kiwiii-server
Author: Seiji Matsuoka
Author-email: mojaie@aol.com
License: MIT
Keywords: drug-discovery cheminformatics api-server
Platform: UNKNOWN
Classifier: Development Status :: 3 - Alpha
Classifier: Intended Audience :: Science/Research
Classifier: Topic :: Scientific/Engineering :: Chemistry
Classifier: Topic :: Scientific/Engineering :: Bio-Informatics
Classifier: License :: OSI Approved :: MIT License
Classifier: Programming Language :: Python
Classifier: Programming Language :: Python :: 3.5
Classifier: Programming Language :: Python :: 3.6
Requires-Python: >=3.5
Requires-Dist: chorus
Requires-Dist: pandas
Requires-Dist: python-louvain
Requires-Dist: tornado
Requires-Dist: xlsxwriter
